pi_shell-1.0.6.dist-info/licenses/LICENSE
pi_shell_tool/__init__.py
pi_shell_tool/main.py
pi_shell-1.0.6.dist-info/METADATA
pi_shell-1.0.6.dist-info/WHEEL
pi_shell-1.0.6.dist-info/entry_points.txt
pi_shell-1.0.6.dist-info/top_level.txt
pi_shell-1.0.6.dist-info/RECORD
