Metadata-Version: 2.4
Name: pi-shell
Version: 1.0.6
Summary: A CLI tool for managing multiple Raspberry Pi devices over SSH
Author-email: Ian McCutcheon <your.email@example.com>
License: MIT
Project-URL: Homepage, https://github.com/mcyork/pi-shell
Project-URL: Repository, https://github.com/mcyork/pi-shell
Project-URL: Issues, https://github.com/mcyork/pi-shell/issues
Keywords: raspberry-pi,ssh,remote,management,cli,iot
Classifier: Development Status :: 4 - Beta
Classifier: Intended Audience :: Developers
Classifier: Intended Audience :: System Administrators
Classifier: License :: OSI Approved :: MIT License
Classifier: Operating System :: MacOS
Classifier: Operating System :: POSIX :: Linux
Classifier: Programming Language :: Python :: 3
Classifier: Programming Language :: Python :: 3.6
Classifier: Programming Language :: Python :: 3.7
Classifier: Programming Language :: Python :: 3.8
Classifier: Programming Language :: Python :: 3.9
Classifier: Programming Language :: Python :: 3.10
Classifier: Programming Language :: Python :: 3.11
Classifier: Programming Language :: Python :: 3.12
Classifier: Topic :: System :: Systems Administration
Classifier: Topic :: Utilities
Requires-Python: >=3.6
License-File: LICENSE
Requires-Dist: paramiko>=2.7.0
Requires-Dist: PyYAML>=5.1
Requires-Dist: cryptography>=3.0
Provides-Extra: dev
Requires-Dist: pytest>=6.0; extra == "dev"
Requires-Dist: black>=22.0; extra == "dev"
Requires-Dist: flake8>=4.0; extra == "dev"
Dynamic: license-file
